open_in_new_tab/__init__.py
open_in_new_tab/open_in_new_tab.py
open_in_new_tab/plugin.py
open_in_new_tab/css/open_in_new_tab.css
open_in_new_tab/js/open_in_new_tab.js
mkdocs_open_in_new_tab-1.0.8.dist-info/LICENSE
mkdocs_open_in_new_tab-1.0.8.dist-info/METADATA
mkdocs_open_in_new_tab-1.0.8.dist-info/WHEEL
mkdocs_open_in_new_tab-1.0.8.dist-info/entry_points.txt
mkdocs_open_in_new_tab-1.0.8.dist-info/top_level.txt
mkdocs_open_in_new_tab-1.0.8.dist-info/RECORD
