Metadata-Version: 2.1
Name: mkdocs-open-in-new-tab
Version: 1.0.8
Summary: MkDocs plugin to open outgoing links and PDFs in new tab.
Home-page: https://github.com/JakubAndrysek/mkdocs-open-in-new-tab
Author: Jakub Andrýsek
Author-email: email@kubaandrysek.cz
License: MIT
Keywords: mkdocs plugin,open in new tab,mkdocs,plugin,relative links,links
Classifier: License :: OSI Approved :: MIT License
Classifier: Programming Language :: Python :: 3.7
Classifier: Programming Language :: Python :: 3.8
Classifier: Programming Language :: Python :: 3.9
Classifier: Programming Language :: Python :: 3.10
Classifier: Programming Language :: Python :: 3.11
Classifier: Programming Language :: Python :: 3.12
Classifier: Operating System :: OS Independent
Requires-Python: >=3.7
License-File: LICENSE
Requires-Dist: mkdocs
Provides-Extra: dev
Requires-Dist: mkdocs-material~=9.5.27; extra == "dev"
Requires-Dist: mkdocs-glightbox~=0.4.0; extra == "dev"
Requires-Dist: mkdocs-git-revision-date-localized-plugin~=1.2.6; extra == "dev"
Requires-Dist: setuptools~=70.0.0; extra == "dev"
Requires-Dist: build~=1.2.2; extra == "dev"
Requires-Dist: twine~=5.1.1; extra == "dev"
